tldc/__init__.py
tldc/assistant.py
tldc/clean_click.py
tldc/constants.py
tldc/context.py
tldc/db.py
tldc/dirtree.py
tldc/logger.py
tldc/main.py
tldc/providers/__init__.py
tldc/providers/ollama.py
tldc/providers/xai.py
tldc-0.9.2.dist-info/METADATA
tldc-0.9.2.dist-info/WHEEL
tldc-0.9.2.dist-info/entry_points.txt
tldc-0.9.2.dist-info/licenses/LICENSE.md
tldc-0.9.2.dist-info/RECORD
