Metadata-Version: 2.4
Name: tldc
Version: 0.9.2
Summary: too lazy; didn't code
Author-email: unic0rn <mirek.kaim@gmail.com>
License-File: LICENSE.md
Requires-Python: >=3.10
Requires-Dist: click==8.3.0
Requires-Dist: xai-sdk==1.2.0
